{
  "project_info": {
    "project_number": "837219363259",
    "project_id": "mypet-f055e",
    "storage_bucket": "mypet-f055e.appspot.com"
  },
  "client": [
    {
      "client_info": {
        "mobilesdk_app_id": "1:837219363259:android:a0889793a5029489f53c9e",
        "android_client_info": {
          "package_name": "com.aplicacion.mypet"
        }
      },
      "oauth_client": [
        {
          "client_id": "837219363259-4n2eqdnumhmseep53gfbore5ta0009p2.apps.googleusercontent.com",
          "client_type": 3
        }
      ],
      "api_key": [
        {
          "current_key": "AIzaSyD2LE6nFPmOpuvvyaTQgG2d_iJxOdesRIc"
        }
      ],
      "services": {
        "appinvite_service": {
          "other_platform_oauth_client": [
            {
              "client_id": "837219363259-4n2eqdnumhmseep53gfbore5ta0009p2.apps.googleusercontent.com",
              "client_type": 3
            }
          ]
        }
      }
    }
  ],
  "configuration_version": "1"
}